rtl/alu.sv
module alu (
    //from decoder
    input logic [2:0] opcode,
    input logic [2:0] funct,
    input logic [2:0] imm,

    //from register file
    input logic [7:0] r1,
    input logic [7:0] r2,
    input logic carry_in,

    //out
    output logic [7:0] alu_out,
    output logic [4:0] alu_flags,
    output logic write_flags_en
);

logic signed [7:0] r1_s = r1;
logic signed [7:0] r2_s = r2;
logic unsigned [7:0] r1_u = r1;
logic unsigned [7:0] r2_u = r2;

always_comb begin
    unique case (opcode)
        3'b110: begin
            {alu_flags[4], alu_out} = r1 + r2;
            write_flags_en = 1'b1;
        end
        3'b100: begin
            alu_flags[3:0] = {r1_u < r2_u, r1_u > r2_u, r1_s < r2_s, r1_s > r2_s};
            write_flags_en = 1'b1;
        end
        3'b010: alu_out = r2;
        3'b101: begin
            if (imm[2]) begin
                unique case (imm[1:0])
                    2'b00: alu_out = r1 >> 1;
                    2'b01: alu_out = r1 >> 2;
                    2'b10: alu_out = r1 >> 3;
                    2'b11: alu_out = r1 >> 4;
                endcase
            end
            else begin
                unique case (imm[1:0])
                    2'b00: {alu_flags[4], alu_out} = {r1, 1'b0};
                    2'b01: {alu_flags[4], alu_out} = {r1[6:0], 2'b0};
                    2'b10: {alu_flags[4], alu_out} = {r1[5:0], 3'b0};
                    2'b11: {alu_flags[4], alu_out} = {r1[4:0], 4'b0};
                endcase
                write_flags_en = 1'b1;
            end
        end
        3'b000: begin
            unique case (imm) inside
                [3'b001:3'b110]: alu_out = {5'b0, imm};
                3'b111: alu_out = 8'b11111111;
                default: alu_out = 8'b0;
            endcase
        end
        3'b111: begin
            {alu_flags[4], alu_out} = r1 + {6'b0, imm[1:0]};
            write_flags_en = 1'b1;
        end
        3'b011: begin
            unique case (funct)
                3'b000: alu_out = $countones(r1);
                3'b001: alu_out = ~r1;
                3'b010: alu_out = r1 ^ r2;
                3'b011: alu_out = r1 & r2;
                3'b100: begin
                    {alu_flags[4], alu_out} = r1 + r2 + {7'b0, carry_in};
                    write_flags_en = 1'b1;
                end
                3'b101: alu_out = r2 - r1;
                3'b110: begin
                    {alu_flags[4], alu_out} = {r1, carry_in};
                    write_flags_en = 1'b1;
                end
                default: alu_out = 8'b0;
            endcase
        end
        default: begin
            alu_flags = 5'b0;
            alu_out = 8'b0;
            write_flags_en = 1'b0;
        end
    endcase
end

endmodule

tb/alu_tb.sv
module alu_tb;

// Signals
logic [2:0] opcode;
logic [2:0] funct;
logic [7:0] r1;
logic [7:0] r2;
logic [2:0] imm;
logic carry_in;
logic [7:0] alu_out;
logic [4:0] alu_flags;
logic write_flags_en;

// Instantiate ALU
alu dut (
    .opcode(opcode),
    .funct(funct),
    .r1(r1),
    .r2(r2),
    .imm(imm),
    .carry_in(carry_in),
    .alu_out(alu_out),
    .alu_flags(alu_flags),
    .write_flags_en(write_flags_en)
);

initial begin
    $dumpfile("dump/alu_dump.vcd");
    $dumpvars(0, alu_tb);

    $display("Starting ALU Testbench");

    // Test ADD (opcode 110) - addition without carry input
    opcode = 3'b110;
    r1 = 8'd10; r2 = 8'd5; carry_in = 0;
    #1; $display("ADD (no carry_in): r1=%d, r2=%d, carry_in=%b, out=%d, carry_out=%b", r1, r2, carry_in, alu_out, alu_flags[4]);
    r1 = 8'd255; r2 = 8'd1; carry_in = 1; // carry_in ignored
    #1; $display("ADD (carry_in ignored): r1=%d, r2=%d, carry_in=%b, out=%d, carry_out=%b", r1, r2, carry_in, alu_out, alu_flags[4]);

    // Test CMP (opcode 100)
    opcode = 3'b100;
    r1 = 8'd10; r2 = 8'd5;
    #1; $display("CMP: r1=%d, r2=%d, flags=%b (u< u> s< s>)", r1, r2, alu_flags[3:0]);
    r1 = 8'd5; r2 = 8'd10;
    #1; $display("CMP: r1=%d, r2=%d, flags=%b", r1, r2, alu_flags[3:0]);
    r1 = 8'b10000000; r2 = 8'b00000001; // signed comparison
    #1; $display("CMP signed: r1=%d, r2=%d, flags=%b", r1, r2, alu_flags[3:0]);

    // Test MOV (opcode 010)
    opcode = 3'b010;
    r1 = 8'd42;
    #1; $display("MOV: r1=%d, out=%d", r1, alu_out);

    // Test Shifts (opcode 101)
    opcode = 3'b101;
    imm = 3'b100; // right shift 1
    r1 = 8'b10101010;
    #1; $display("RSH 1: r1=%b, out=%b", r1, alu_out);
    imm = 3'b101; // right shift 2
    #1; $display("RSH 2: r1=%b, out=%b", r1, alu_out);
    imm = 3'b000; // left shift 1
    #1; $display("LSH 1: r1=%b, out=%b, carry_out=%b", r1, alu_out, alu_flags[4]);
    imm = 3'b001; // left shift 2
    #1; $display("LSH 2: r1=%b, out=%b, carry_out=%b", r1, alu_out, alu_flags[4]);

    // Test IMM (opcode 000)
    opcode = 3'b000;
    imm = 3'b001;
    #1; $display("IMM 1: imm=%b, out=%b", imm, alu_out);
    imm = 3'b111;
    #1; $display("IMM 7: imm=%b, out=%b", imm, alu_out);

    // Test ADD IMM (opcode 111)
    opcode = 3'b111;
    r1 = 8'd10; imm = 3'd2;
    #1; $display("ADD IMM: r1=%d, imm=%d, out=%d, carry_out=%b", r1, imm, alu_out, alu_flags[4]);

    // Test other ops (opcode 011)
    opcode = 3'b011;
    funct = 3'b000; // countones(r1 ^ r2)
    r1 = 8'b10101010; r2 = 8'b01010101;
    #1; $display("COUNTONES XOR: r1=%b, r2=%b, out=%d", r1, r2, alu_out);
    funct = 3'b001; // ~r1
    #1; $display("NOT: r1=%b, out=%b", r1, alu_out);
    funct = 3'b010; // r1 ^ r2
    #1; $display("XOR: r1=%b, r2=%b, out=%b", r1, r2, alu_out);
    funct = 3'b011; // r1 & r2
    #1; $display("AND: r1=%b, r2=%b, out=%b", r1, r2, alu_out);
    funct = 3'b100; // add with carry
    carry_in = 1;
    #1; $display("ADD CARRY: r1=%d, r2=%d, carry_in=%b, out=%d, carry_out=%b", r1, r2, carry_in, alu_out, alu_flags[4]);
    funct = 3'b101; // sub (assuming)
    #1; $display("SUB: r1=%d, r2=%d, out=%d", r1, r2, alu_out);
    funct = 3'b110; // lshiftc
    carry_in = 1;
    #1; $display("LSHIFTC: r1=%b, carry_in=%b, out=%b", r1, carry_in, alu_out);

    $display("ALU Testbench Complete");
    $finish;
end

endmodule

dump/alu_dump.vcd
$version Generated by VerilatedVcd $end
$timescale 1ps $end
 $scope module alu_tb $end
  $var wire 3 " opcode [2:0] $end
  $var wire 3 # funct [2:0] $end
  $var wire 8 $ r1 [7:0] $end
  $var wire 8 % r2 [7:0] $end
  $var wire 3 & imm [2:0] $end
  $var wire 1 ' carry_in $end
  $var wire 8 ( alu_out [7:0] $end
  $var wire 5 ) alu_flags [4:0] $end
  $var wire 1 * write_flags_en $end
  $scope module dut $end
   $var wire 3 " opcode [2:0] $end
   $var wire 3 # funct [2:0] $end
   $var wire 8 $ r1 [7:0] $end
   $var wire 8 % r2 [7:0] $end
   $var wire 3 & imm [2:0] $end
   $var wire 1 ' carry_in $end
   $var wire 8 ( alu_out [7:0] $end
   $var wire 5 ) alu_flags [4:0] $end
   $var wire 1 * write_flags_en $end
   $var wire 8 $ r1_s [7:0] $end
   $var wire 8 % r2_s [7:0] $end
   $var wire 8 $ r1_u [7:0] $end
   $var wire 8 % r2_u [7:0] $end
  $upscope $end
 $upscope $end
$enddefinitions $end


#0
b110 "
b000 #
b00001010 $
b00000101 %
b000 &
0'
b00001111 (
b00000 )
1*
#1
b11111111 $
b00000001 %
1'
b00000000 (
b10000 )
#2
b100 "
b00001010 $
b00000101 %
b00101 )
#3
b00000101 $
b00001010 %
b01010 )
#4
b10000000 $
b00000001 %
b00110 )
#5
b010 "
b00101010 $
b00101010 (
b00000 )
0*
#6
b101 "
b10101010 $
b100 &
b01010101 (
#7
b101 &
b00101010 (
#8
b000 &
b01010100 (
b10000 )
1*
#9
b001 &
b10101000 (
b00000 )
#10
b000 "
b00000001 (
0*
#11
b111 &
b11111111 (
#12
b111 "
b00001010 $
b010 &
b00001100 (
1*
#13
b011 "
b10101010 $
b01010101 %
b00001000 (
0*
#14
b001 #
b01010101 (
#15
b010 #
b11111111 (
#16
b011 #
b00000000 (
#17
b100 #
b10000 )
1*
#18
b101 #
b01010101 (
b00000 )
0*
#19
b110 #
b10000 )
1*
