rtl/next_pc.sv
module next_pc (
    //from top-level module
    input logic [9:0] current_pc,

    //from register file
    input logic [6:0] flags , //carry flag unused in branching so only 7 bits passed

    //from instruction memory
    input logic [17:0] jump_target,
    
    //from stack
    input logic [9:0] top_address,

    //from decoder
    input logic pc_write_en,

    output logic [9:0] new_pc
);

logic [9:0] pc_p1;
assign pc_p1 = current_pc + 10'b1;

//1 appended for unconditional jumps
logic [7:0] extended_flags;
assign extended_flags = {1'b1, flags};

logic ltu, gtu, lts, gts;
assign ltu = jump_target[11] & ~jump_target[9];
assign gtu = jump_target[10] & ~jump_target[9];
assign lts = jump_target[11] & jump_target[9];
assign gts = jump_target[10] & jump_target[9];

logic [8:0] one_hot_code;
assign one_hot_code = {jump_target[16:12], ltu, gtu, lts, gts};

logic [9:0] jump_address;
assign jump_address = {jump_target[8:0], jump_target[17]};

always_comb begin
    new_pc = pc_p1;
    for (int i = 0; i < 9; i++) begin
        if (one_hot_code[i]) begin
            if (pc_write_en) begin
                if ((i < 8) & extended_flags[i]) begin
                    new_pc = jump_address;
                end else if (i == 8) begin
                    new_pc = top_address;
                end
            end
        end
    end
end

endmodule

rtl/register_write_mux.sv
module register_write_mux (
    input logic [7:0] alu_out,
    input logic [7:0] data_mem_out,
    input logic [7:0] stack_out,

    input logic [1:0] write_src,

    output logic [7:0] mux_out
);

always_comb begin
    unique case (write_src)
        2'b01: mux_out = data_mem_out;
        2'b10: mux_out = stack_out;
        default: mux_out = alu_out;
    endcase
end

endmodule

rtl/data_memory.sv
module data_memory (
    input logic clk,

    //from ALU
    input logic [7:0] address,

    //from register file
    input logic [7:0] data_in,

    //from decoder
    input logic write_en,

    output logic [7:0] data_out
);

logic [7:0] core [0:255];

assign data_out = core[address];

always_ff @(posedge clk) begin
    if (write_en) core[address] <= data_in;
end

endmodule

rtl/alu.sv
module alu (
    //from decoder
    input logic [2:0] opcode,
    input logic [2:0] funct,
    input logic [2:0] imm,

    //from register file
    input logic [7:0] r1,
    input logic [7:0] r2,
    input logic carry_in,

    //out
    output logic [7:0] alu_out,
    output logic [4:0] alu_flags,
    output logic write_flags_en
);

logic signed [7:0] r1_s = r1;
logic signed [7:0] r2_s = r2;
logic unsigned [7:0] r1_u = r1;
logic unsigned [7:0] r2_u = r2;

always_comb begin
    alu_flags = 5'b0;
    alu_out = 8'b0;
    write_flags_en = 1'b0;

    unique case (opcode)
        3'b110: begin
            {alu_flags[4], alu_out} = r1 + r2;
            write_flags_en = 1'b1;
        end
        3'b100: begin
            alu_flags[3:0] = {r1_u < r2_u, r1_u > r2_u, r1_s < r2_s, r1_s > r2_s};
            write_flags_en = 1'b1;
        end
        3'b010: alu_out = r2;
        3'b101: begin
            if (imm[2]) begin
                unique case (imm[1:0])
                    2'b00: alu_out = r1 >> 1;
                    2'b01: alu_out = r1 >> 2;
                    2'b10: alu_out = r1 >> 3;
                    2'b11: alu_out = r1 >> 4;
                endcase
            end
            else begin
                unique case (imm[1:0])
                    2'b00: {alu_flags[4], alu_out} = {r1, 1'b0};
                    2'b01: {alu_flags[4], alu_out} = {r1[6:0], 2'b0};
                    2'b10: {alu_flags[4], alu_out} = {r1[5:0], 3'b0};
                    2'b11: {alu_flags[4], alu_out} = {r1[4:0], 4'b0};
                endcase
                write_flags_en = 1'b1;
            end
        end
        3'b000: begin
            unique case (imm) inside
                [3'b001:3'b110]: alu_out = {5'b0, imm};
                3'b111: alu_out = 8'b11111111;
                default: alu_out = 8'b0;
            endcase
        end
        3'b111: begin
            {alu_flags[4], alu_out} = r1 + {6'b0, imm[1:0]};
            write_flags_en = 1'b1;
        end
        3'b011: begin
            unique case (funct)
                3'b000: alu_out = $countones(r1);
                3'b001: alu_out = ~r1;
                3'b010: alu_out = r1 ^ r2;
                3'b011: alu_out = r1 & r2;
                3'b100: begin
                    {alu_flags[4], alu_out} = r1 + r2 + {7'b0, carry_in};
                    write_flags_en = 1'b1;
                end
                3'b101: alu_out = r2 - r1;
                3'b110: begin
                    {alu_flags[4], alu_out} = {r1, carry_in};
                    write_flags_en = 1'b1;
                end
                default: alu_out = 8'b0;
            endcase
        end
        default: begin
            //
        end
    endcase
end

endmodule

rtl/register_file.sv
module register_file (
    input logic clk,

    //from decoder
    input logic [2:0] read1_src,
    input logic [2:0] read2_src,
    input logic [2:0] write_dest,
    input logic write_en,

    //from ALU/data memory/stack
    input logic [7:0] write_data,

    //from ALU
    input logic [4:0] alu_flags,
    input logic write_flags_en,
    
    //to ALU
    output logic [7:0] read1_result,
    output logic [7:0] read2_result,

    output logic [7:0] flags
);

logic [7:0] registers [0:7];
logic [4:0] flag_registers;

assign read1_result = registers[read1_src];
assign read2_result = registers[read2_src];

assign flags[7] = flag_registers[4];
assign flags[3:0] = flag_registers[3:0];

always_ff @(posedge clk) begin
    if (write_en) registers[write_dest] <= write_data;
end

//lt, gt, lts, and gts flags written from ALU
always_ff @(posedge clk) begin
    if (write_flags_en) begin
        flag_registers <= alu_flags;
    end
end

//z, nz, and pos flags set combinationally
assign flags[6] = ~|(registers[0]);
assign flags[5] = |(registers[0]);
assign flags[4] = registers[0][7];

endmodule

rtl/decoder.sv
module decoder (
    //from instruction memory
    input logic [8:0] instruction,

    //to instruction memory
    output logic [5:0] label_address,

    //to ALU
    output logic [2:0] opcode,
    output logic [2:0] funct,
    output logic [2:0] imm,

    //to data memory
    output logic mem_write_en,

    //to pc
    output logic pc_write_en,

    //to register file
    output logic [2:0] read1_src,
    output logic [2:0] read2_src,
    output logic [2:0] write_dest,
    output logic reg_write_en,

    //to stack controller
    output logic stack_controller_op_type,
    output logic [1:0] stack_controller_mask,

    //to register write MUX
    output logic [1:0] write_src
);

assign label_address = instruction[5:0];

assign opcode = instruction[8:6];
assign funct = instruction[2:0];
assign imm = instruction[2:0];

assign mem_write_en = &(instruction[8:6]);

assign pc_write_en = (instruction[8:6] == 3'b001);

assign read1_src = instruction[5:3];
assign read2_src = ((instruction[8] & ~instruction[6]) | (instruction[8:6] == 3'b010)) ? instruction[2:0] : 3'b0; //only read 2nd register for add/cmp/copy
assign write_dest = (instruction[8] ~| instruction[6]) ? instruction[5:3] : 3'b0; //only write to other registers for imm/copy

logic is_cmp = (instruction[8:6] == 3'b100);
logic is_push = ~|{instruction[8:5], instruction[2:0]};
logic is_pop = ~|{instruction[8:6], instruction[2:0]} & instruction[5];
logic is_load = &instruction[8:6] & instruction[2];
logic is_store = &instruction[8:6] & ~instruction[2];
logic is_jump = (instruction[8:6] == 3'b001);

assign reg_write_en = ~|{is_cmp, is_push, is_store, is_jump}; //disable register writing for cmp, push, store, jumps

assign stack_controller_op_type = instruction[5];
assign stack_controller_mask = instruction[4:3];

always_comb begin
    if (is_load) write_src = 2'b01;
    else if (is_pop) write_src = 2'b10;
    else write_src = 2'b00;
end

endmodule

rtl/instruction_memory.sv
module instruction_memory (
    //from pc
    input logic [9:0] pc,

    //from decoder
    input logic [5:0] label_address,
    
    output logic [8:0] instruction,
    output logic [17:0] jump_target
);

logic [8:0] mem [0:1023];
logic [8:0] instruction_mem [0:895];
logic [8:0] label_mem [0:127];

assign instruction_mem = mem[0:895];
assign label_mem = mem[896:1023];

initial begin
    $readmemb("../rtl/programs/branching.bin", mem);
end

assign instruction = mem[pc];
assign jump_target = {label_mem[{label_address, 1'b1}], label_mem[{label_address, 1'b0}]};

endmodule

rtl/top.sv
module top (
    input logic clk,
    input logic start,

    output logic done
);

//instruction memory signals
logic [9:0] pc;

logic [5:0] label_address;

logic [8:0] instruction;
logic [17:0] jump_target;
instruction_memory instruction_memory_inst(
    .pc(pc),
    
    .label_address(label_address),

    .instruction(instruction),
    .jump_target(jump_target)
);

//decoder signals
logic [2:0] opcode;
logic [2:0] funct;
logic [2:0] imm;

logic mem_write_en;

logic pc_write_en;

logic [2:0] read1_src;
logic [2:0] read2_src;
logic [2:0] write_dest;
logic reg_write_en;

logic stack_controller_op_type;
logic [1:0] stack_controller_mask;

logic [1:0] write_src;
decoder decoder_inst(
    .instruction(instruction),
    
    .label_address(label_address),
    
    .opcode(opcode),
    .funct(funct),
    .imm(imm),

    .mem_write_en(mem_write_en),

    .pc_write_en(pc_write_en),

    .read1_src(read1_src),
    .read2_src(read2_src),
    .write_dest(write_dest),
    .reg_write_en(reg_write_en),

    .stack_controller_op_type(stack_controller_op_type),
    .stack_controller_mask(stack_controller_mask),

    .write_src(write_src)
);

//register file signals
logic [7:0] read1_result;
logic [7:0] read2_result;

logic [7:0] register_write_data;

logic [4:0] alu_flags;
logic write_flags_en;
logic [7:0] flags;
register_file register_file_inst(
    .clk(clk),

    .read1_src(read1_src),
    .read2_src(read2_src),
    .write_dest(write_dest),
    .write_en(reg_write_en), 

    .write_data(register_write_data),

    .alu_flags(alu_flags),
    .write_flags_en(write_flags_en),

    .read1_result(read1_result),
    .read2_result(read2_result),

    .flags(flags)
);

//ALU signals
logic [7:0] alu_out;
alu alu_inst(
    .opcode(opcode),
    .funct(funct),
    .imm(imm),

    .r1(read1_result),
    .r2(read2_result),
    .carry_in(flags[7]),

    .alu_out(alu_out),
    .alu_flags(alu_flags),
    .write_flags_en(write_flags_en)
);

//data memory signals
logic [7:0] mem_out;
data_memory data_memory_inst(
    .clk(clk),
    .address(alu_out),
    .data_in(read2_result),
    .write_en(mem_write_en),
    .data_out(mem_out)
);

//register write MUX signals
register_write_mux register_write_mux_inst(
    .alu_out(alu_out),
    .data_mem_out(mem_out),
    .stack_out(8'b0), //todo
    .write_src(write_src),
    .mux_out(register_write_data)
);

//next pc signals
logic [9:0] new_pc;
next_pc next_pc_inst(
    .current_pc(pc),
    .flags(flags[6:0]),
    .jump_target(jump_target),
    .top_address(10'b0), //todo
    .pc_write_en(pc_write_en),
    .new_pc(new_pc)
);

typedef enum {
    exec, stack, halted
} states;

states current_state;
initial begin
    current_state = halted;
end

always_ff @(posedge clk) begin
    unique case (current_state)
        exec: begin
            if (instruction == 9'b011000111) begin
                current_state <= halted;
            end
            else begin
                pc <= new_pc;
            end
        end

        stack: begin

        end

        halted: begin
            if (start) current_state <= exec;
        end

        default: current_state <= halted;
    endcase
end

endmodule

tb/top_tb.sv
module top_tb;

bit clk;
logic start;
logic done;
top dut(.*);

function void display_info();
    $display("State at start of cycle:");
    $display("PC: %d", dut.pc);
    $display("Instruction: %b", dut.instruction);
    $display("Registers: [%d, %d, %d, %d, %d, %d, %d, %d]", dut.register_file_inst.registers[0], dut.register_file_inst.registers[1], dut.register_file_inst.registers[2], dut.register_file_inst.registers[3], dut.register_file_inst.registers[4], dut.register_file_inst.registers[5], dut.register_file_inst.registers[6], dut.register_file_inst.registers[7]);
    $display("Memory contents: [%d, %d, %d, %d, %d, %d, %d, %d, %d, %d]", dut.data_memory_inst.core[0], dut.data_memory_inst.core[1], dut.data_memory_inst.core[2], dut.data_memory_inst.core[3], dut.data_memory_inst.core[4], dut.data_memory_inst.core[5], dut.data_memory_inst.core[6], dut.data_memory_inst.core[7], dut.data_memory_inst.core[8], dut.data_memory_inst.core[9], );
    $display();
endfunction

task automatic advance_clk();
    #5 clk = ~clk;
    #5 clk = ~clk;
endtask

logic [12:0] count = 0;
logic debug_pause = 1;

initial begin 
    $dumpfile("../dump/top_dump.vcd");
    $dumpvars(0, top_tb);

    $display("Starting top-level testbench");
    start = 1'b1;
    advance_clk();

    #10 clk = ~clk;
    $display("Instruction number: %d", count++);
    display_info();

    repeat (16) begin
        advance_clk();

        if (count == 2 & debug_pause) begin
            $display("inspection: %b %b %b", dut.next_pc_inst.one_hot_code, dut.next_pc_inst.extended_flags, dut.next_pc_inst.jump_target);
        end

        $display("Instruction number: %d", count++);
        display_info();

        if (done) begin
            $display("Finished program");
            $finish;
        end
    end

    $finish;
end

endmodule

dump/top_dump.vcd
$version Generated by VerilatedVcd $end
$timescale 1ps $end
 $scope module top_tb $end
  $var wire 1 S clk $end
  $var wire 1 T start $end
  $var wire 1 W done $end
  $var wire 13 U count [12:0] $end
  $var wire 1 X debug_pause $end
  $scope module dut $end
   $var wire 1 S clk $end
   $var wire 1 T start $end
   $var wire 1 W done $end
   $var wire 10 " pc [9:0] $end
   $var wire 6 # label_address [5:0] $end
   $var wire 9 $ instruction [8:0] $end
   $var wire 18 % jump_target [17:0] $end
   $var wire 3 & opcode [2:0] $end
   $var wire 3 ' funct [2:0] $end
   $var wire 3 ' imm [2:0] $end
   $var wire 1 ( mem_write_en $end
   $var wire 1 ) pc_write_en $end
   $var wire 3 * read1_src [2:0] $end
   $var wire 3 + read2_src [2:0] $end
   $var wire 3 , write_dest [2:0] $end
   $var wire 1 - reg_write_en $end
   $var wire 1 . stack_controller_op_type $end
   $var wire 2 / stack_controller_mask [1:0] $end
   $var wire 2 0 write_src [1:0] $end
   $var wire 8 1 read1_result [7:0] $end
   $var wire 8 2 read2_result [7:0] $end
   $var wire 8 3 register_write_data [7:0] $end
   $var wire 5 4 alu_flags [4:0] $end
   $var wire 1 5 write_flags_en $end
   $var wire 8 6 flags [7:0] $end
   $var wire 8 7 alu_out [7:0] $end
   $var wire 8 8 mem_out [7:0] $end
   $var wire 10 9 new_pc [9:0] $end
   $var wire 32 V current_state [31:0] $end
   $scope module alu_inst $end
    $var wire 3 & opcode [2:0] $end
    $var wire 3 ' funct [2:0] $end
    $var wire 3 ' imm [2:0] $end
    $var wire 8 1 r1 [7:0] $end
    $var wire 8 2 r2 [7:0] $end
    $var wire 1 : carry_in $end
    $var wire 8 7 alu_out [7:0] $end
    $var wire 5 4 alu_flags [4:0] $end
    $var wire 1 5 write_flags_en $end
    $var wire 8 1 r1_s [7:0] $end
    $var wire 8 2 r2_s [7:0] $end
    $var wire 8 1 r1_u [7:0] $end
    $var wire 8 2 r2_u [7:0] $end
   $upscope $end
   $scope module data_memory_inst $end
    $var wire 1 S clk $end
    $var wire 8 7 address [7:0] $end
    $var wire 8 2 data_in [7:0] $end
    $var wire 1 ( write_en $end
    $var wire 8 8 data_out [7:0] $end
   $upscope $end
   $scope module decoder_inst $end
    $var wire 9 $ instruction [8:0] $end
    $var wire 6 # label_address [5:0] $end
    $var wire 3 & opcode [2:0] $end
    $var wire 3 ' funct [2:0] $end
    $var wire 3 ' imm [2:0] $end
    $var wire 1 ( mem_write_en $end
    $var wire 1 ) pc_write_en $end
    $var wire 3 * read1_src [2:0] $end
    $var wire 3 + read2_src [2:0] $end
    $var wire 3 , write_dest [2:0] $end
    $var wire 1 - reg_write_en $end
    $var wire 1 . stack_controller_op_type $end
    $var wire 2 / stack_controller_mask [1:0] $end
    $var wire 2 0 write_src [1:0] $end
    $var wire 1 ; is_cmp $end
    $var wire 1 < is_push $end
    $var wire 1 = is_pop $end
    $var wire 1 > is_load $end
    $var wire 1 ? is_store $end
    $var wire 1 @ is_jump $end
   $upscope $end
   $scope module instruction_memory_inst $end
    $var wire 10 " pc [9:0] $end
    $var wire 6 # label_address [5:0] $end
    $var wire 9 $ instruction [8:0] $end
    $var wire 18 % jump_target [17:0] $end
   $upscope $end
   $scope module next_pc_inst $end
    $var wire 10 " current_pc [9:0] $end
    $var wire 7 A flags [6:0] $end
    $var wire 18 % jump_target [17:0] $end
    $var wire 10 Y top_address [9:0] $end
    $var wire 1 ) pc_write_en $end
    $var wire 10 9 new_pc [9:0] $end
    $var wire 10 B pc_p1 [9:0] $end
    $var wire 8 C extended_flags [7:0] $end
    $var wire 1 D ltu $end
    $var wire 1 E gtu $end
    $var wire 1 F lts $end
    $var wire 1 G gts $end
    $var wire 9 H one_hot_code [8:0] $end
    $var wire 10 I jump_address [9:0] $end
   $upscope $end
   $scope module register_file_inst $end
    $var wire 1 S clk $end
    $var wire 3 * read1_src [2:0] $end
    $var wire 3 + read2_src [2:0] $end
    $var wire 3 , write_dest [2:0] $end
    $var wire 1 - write_en $end
    $var wire 8 3 write_data [7:0] $end
    $var wire 5 4 alu_flags [4:0] $end
    $var wire 1 5 write_flags_en $end
    $var wire 8 1 read1_result [7:0] $end
    $var wire 8 2 read2_result [7:0] $end
    $var wire 8 6 flags [7:0] $end
    $var wire 8 J registers[0] [7:0] $end
    $var wire 8 K registers[1] [7:0] $end
    $var wire 8 L registers[2] [7:0] $end
    $var wire 8 M registers[3] [7:0] $end
    $var wire 8 N registers[4] [7:0] $end
    $var wire 8 O registers[5] [7:0] $end
    $var wire 8 P registers[6] [7:0] $end
    $var wire 8 Q registers[7] [7:0] $end
    $var wire 5 R flag_registers [4:0] $end
   $upscope $end
   $scope module register_write_mux_inst $end
    $var wire 8 7 alu_out [7:0] $end
    $var wire 8 8 data_mem_out [7:0] $end
    $var wire 8 Z stack_out [7:0] $end
    $var wire 2 0 write_src [1:0] $end
    $var wire 8 3 mux_out [7:0] $end
   $upscope $end
  $upscope $end
 $upscope $end
$enddefinitions $end


#0
b0000000000 "
b000010 #
b011000010 $
b001000000000000001 %
b011 &
b010 '
0(
0)
b000 *
b000 +
b000 ,
1-
0.
b00 /
b00 0
b00000000 1
b00000000 2
b00000000 3
b00000 4
05
b01000000 6
b00000000 7
b00000000 8
b0000000001 9
0:
0;
0<
0=
0>
0?
0@
b1000000 A
b0000000001 B
b11000000 C
0D
0E
0F
0G
b010000000 H
b0000000010 I
b00000000 J
b00000000 K
b00000000 L
b00000000 M
b00000000 N
b00000000 O
b00000000 P
b00000000 Q
b00000 R
0S
1T
b0000000000000 U
b00000000000000000000000000000010 V
0W
1X
b0000000000 Y
b00000000 Z
#5
1S
b00000000000000000000000000000000 V
#10
0S
#20
b0000000001 "
b111000 #
b010111000 $
b000000000000000000 %
b010 &
b000 '
b111 *
b111 ,
1.
b11 /
b0000000010 9
b0000000010 B
b000000000 H
b0000000000 I
1S
b0000000000001 U
#25
0S
#30
b0000000010 "
b000100 #
b001000100 $
b001000000000000011 %
b001 &
b100 '
1)
b000 *
b000 ,
0-
0.
b00 /
b0000000110 9
1@
b0000000011 B
b010000000 H
b0000000110 I
1S
b0000000000010 U
#35
0S
#40
b0000000110 "
b001001 #
b000001001 $
b000100000000001010 %
b000 &
b001 '
0)
b001 *
b001 ,
1-
b01 /
b00000001 3
b00000001 7
b0000000111 9
0@
b0000000111 B
b001000000 H
b0000010100 I
1S
b0000000000011 U
#45
0S
#50
b0000000111 "
b000001 #
b010000001 $
b001000000000000000 %
b010 &
b000 *
b001 +
b000 ,
b00 /
b00000001 2
b0000001000 9
b0000001000 B
b010000000 H
b0000000000 I
b00000001 K
1S
b0000000000100 U
#55
0S
#60
b0000001000 "
b111000 #
b111111000 $
b000000000000000000 %
b111 &
b000 '
1(
b111 *
b000 +
0-
1.
b11 /
b00000000 3
15
b00100000 6
b00000000 7
b0000001001 9
1?
b0100000 A
b0000001001 B
b10100000 C
b000000000 H
b00000001 J
1S
b0000000000101 U
#65
0S
#70
b0000001001 "
b000101 #
b001000101 $
b001000000000000101 %
b001 &
b101 '
0(
1)
b000 *
0.
b00 /
b00000001 1
05
b00000001 8
b0000001010 9
0?
1@
b0000001010 B
b010000000 H
b0000001010 I
1S
b0000000000110 U
#75
0S
#80
b0000001010 "
b000010 #
b011000010 $
b001000000000000001 %
b011 &
b010 '
0)
1-
b0000001011 9
0@
b0000001011 B
b0000000010 I
1S
b0000000000111 U
#85
0S
#90
b0000001011 "
b000110 #
b001000110 $
b100100000000000110 %
b001 &
b110 '
1)
0-
b00000000 1
b00000000 2
b01000000 6
b0000001101 9
1@
b1000000 A
b0000001100 B
b11000000 C
b001000000 H
b0000001101 I
b00000000 J
1S
b0000000001000 U
#95
0S
#100
b0000001101 "
b010011 #
b000010011 $
b000000100000011001 %
b000 &
b011 '
0)
b010 *
b010 ,
1-
b10 /
b00000011 3
b00000011 7
b00000000 8
b0000001110 9
0@
b0000001110 B
1D
b000001000 H
b0000110010 I
1S
b0000000001001 U
#105
0S
#110
b0000001110 "
b000010 #
b010000010 $
b001000000000000001 %
b010 &
b010 '
b000 *
b010 +
b000 ,
b00 /
b00000011 2
b0000001111 9
b0000001111 B
0D
b010000000 H
b0000000010 I
b00000011 L
1S
b0000000001010 U
#115
0S
#120
b0000001111 "
b001001 #
b001001001 $
b000100000000001010 %
b001 &
b001 '
1)
b001 *
b000 +
0-
b01 /
b00000001 1
b00000000 3
b00100000 6
b00000000 7
b00000001 8
b0000010000 9
1@
b0100000 A
b0000010000 B
b10100000 C
b001000000 H
b0000010100 I
b00000011 J
1S
b0000000001011 U
#125
0S
#130
b0000010000 "
b000001001 $
b000 &
0)
b001 ,
1-
b00000001 3
b00000001 7
b00000000 8
b0000010001 9
0@
b0000010001 B
1S
b0000000001100 U
#135
0S
#140
b0000010001 "
b000001 #
b010000001 $
b001000000000000000 %
b010 &
b000 *
b001 +
b000 ,
b00 /
b00000011 1
b00000001 2
b0000010010 9
b0000010010 B
b010000000 H
b0000000000 I
1S
b0000000001101 U
#145
0S
#150
b0000010010 "
b111001 #
b111111001 $
b000000000000000000 %
b111 &
1(
b111 *
b000 +
0-
1.
b11 /
b00000000 1
15
b0000010011 9
1?
b0000010011 B
b000000000 H
b00000001 J
1S
b0000000001110 U
#155
0S
#160
b0000010011 "
b001010 #
b001001010 $
b101000000000001011 %
b001 &
b010 '
0(
1)
b001 *
0.
b01 /
b00000001 1
b00000000 3
05
b00000000 7
b00000001 8
b0000010111 9
0?
1@
b0000010100 B
b010000000 H
b0000010111 I
1S
b0000000001111 U
#165
0S
#170
b0000010111 "
b001101 #
b000001101 $
b001000000000010001 %
b000 &
b101 '
0)
b001 ,
1-
b00000101 3
b00000101 7
b00000000 8
b0000011000 9
0@
b0000011000 B
b0000100010 I
1S
b0000000010000 U
#175
0S
#180
b0000011000 "
b010011 #
b000010011 $
b000000100000011001 %
b011 '
b010 *
b010 ,
b10 /
b00000011 1
b00000011 3
b00000011 7
b0000011001 9
b0000011001 B
1D
b000001000 H
b0000110010 I
b00000101 K
1S
b0000000010001 U
